wagtail_uplift/__init__.py
wagtail_uplift/wagtail_hooks.py
wagtail_uplift/static/css/wagtail_uplift.css
wagtail_uplift/static/css/wagtail_uplift.min.css
wagtail_uplift/templates/wagtailadmin/base.html
wagtail_uplift-0.0.9.dist-info/DESCRIPTION.rst
wagtail_uplift-0.0.9.dist-info/METADATA
wagtail_uplift-0.0.9.dist-info/RECORD
wagtail_uplift-0.0.9.dist-info/WHEEL
wagtail_uplift-0.0.9.dist-info/metadata.json
wagtail_uplift-0.0.9.dist-info/top_level.txt
