Metadata-Version: 2.0
Name: wagtail-uplift
Version: 0.0.9
Summary: A custom theme for Wagtail’s dashboard.
Home-page: https://github.com/l1f7/wagtail_uplift
Author: Lift Interactive
Author-email: dev+pypi@liftinteractive.com
License: BSD License
Platform: UNKNOWN
Classifier: Development Status :: 5 - Production/Stable
Classifier: Environment :: Web Environment
Classifier: Intended Audience :: Developers
Classifier: License :: OSI Approved :: BSD License
Classifier: Operating System :: OS Independent
Classifier: Programming Language :: Python
Classifier: Programming Language :: Python :: 2
Classifier: Programming Language :: Python :: 2.7
Classifier: Programming Language :: Python :: 3
Classifier: Programming Language :: Python :: 3.3
Classifier: Programming Language :: Python :: 3.4
Classifier: Programming Language :: Python :: 3.5
Classifier: Framework :: Django
Classifier: Framework :: Django :: 1.8
Classifier: Framework :: Django :: 1.9
Classifier: Topic :: Internet :: WWW/HTTP :: Site Management
